<Properties StartupConfiguration="{D512E57B-8CCA-E799-87AB-8E6B846509DE}|">
  <MonoDevelop.Ide.ItemProperties.Assembly-CSharp PreferredExecutionTarget="Unity.Editor" />
  <MonoDevelop.Ide.Workbench ActiveDocument="Assets/Scripts/PlayerShoot.cs">
    <Files>
      <File FileName="Assets/Scripts/Projectile.cs" Line="52" Column="14" />
      <File FileName="Assets/Scripts/PlayerShoot.cs" Line="16" Column="77" />
    </Files>
  </MonoDevelop.Ide.Workbench>
  <MonoDevelop.Ide.Workspace ActiveConfiguration="Debug" />
  <MonoDevelop.Ide.DebuggingService.Breakpoints>
    <BreakpointStore />
  </MonoDevelop.Ide.DebuggingService.Breakpoints>
  <MonoDevelop.Ide.DebuggingService.PinnedWatches />
  <MultiItemStartupConfigurations />
</Properties>